LICENSE
README.md
setup.py
jjy_tap_mysql.egg-info/PKG-INFO
jjy_tap_mysql.egg-info/SOURCES.txt
jjy_tap_mysql.egg-info/dependency_links.txt
jjy_tap_mysql.egg-info/entry_points.txt
jjy_tap_mysql.egg-info/requires.txt
jjy_tap_mysql.egg-info/top_level.txt
tap_mysql/__init__.py
tap_mysql/connection.py
tap_mysql/discover_utils.py
tap_mysql/jjy_custom_singer.py
tap_mysql/stream_utils.py
tap_mysql/sync_strategies/binlog.py
tap_mysql/sync_strategies/common.py
tap_mysql/sync_strategies/full_table.py
tap_mysql/sync_strategies/incremental.py