Metadata-Version: 2.1
Name: jjy-tap-mysql
Version: 1.0.0
Summary: Singer.io tap for extracting data from MySQL & MariaDB - PipelineWise compatible
Home-page: 
Author: 
License: UNKNOWN
Platform: UNKNOWN
Classifier: License :: OSI Approved :: GNU Affero General Public License v3
Classifier: Programming Language :: Python :: 3 :: Only
Provides-Extra: test
License-File: LICENSE
